README.rst
setup.cfg
setup.py
binance/__init__.py
binance/api_def.py
binance/client.py
binance/exceptions.py
binance/request_handler.py
binance/utils.py
binance/websockets.py
binance/endpoints/__init__.py
binance/endpoints/futures.py
binance/endpoints/margin_trade.py
binance/endpoints/market_data.py
binance/endpoints/spot_trade.py
binance/endpoints/wallet.py
binancepy.egg-info/PKG-INFO
binancepy.egg-info/SOURCES.txt
binancepy.egg-info/dependency_links.txt
binancepy.egg-info/requires.txt
binancepy.egg-info/top_level.txt