Metadata-Version: 1.2
Name: binancepy
Version: 0.0.1b0
Summary: Binance REST API python implementation
Home-page: https://github.com/vinitjames/binancepy
Author: Vinit James
Author-email: vinit.james24@gmail.com
License: MIT
Keywords: binance exchange rest api bitcoin ethereum btc eth neo
Platform: UNKNOWN
Classifier: Intended Audience :: Developers
Classifier: License :: OSI Approved :: MIT License
Classifier: Operating System :: OS Independent
Classifier: Programming Language :: Python :: 3
Classifier: Programming Language :: Python :: 3.5
Classifier: Programming Language :: Python :: 3.6
Classifier: Programming Language :: Python :: 3.7
Classifier: Programming Language :: Python
Classifier: Topic :: Software Development :: Libraries :: Python Modules
Requires-Python: >=3.0
